---
layout: post
title:  "Java语法糖"
date:    2017-05-31 15:28:31
author: zhangtejun
categories: zhangtejun
---
### Java语法糖
##### 什么是语法糖？
摘自百度：语法糖（Syntactic sugar），也译为糖衣语法，是由英国计算机科学家彼得·约翰·兰达（Peter J. Landin）发明的一个术语，
指计算机语言中添加的某种语法，这种语法对语言的功能并没有影响，但是更方便程序员使用。通常来说使用语法糖能够增加程序的可读性，从而减少程序代码出错的机会。

语法糖是一种几乎每种语言或多或少都提供过的一些方便程序员开发代码的语法，它只是编译器实现的一些小把戏罢了，
编译期间以特定的字节码或者特定的方式对这些语法做一些处理，开发者就可以直接方便地使用了。这些语法糖虽然不
会提供实质性的功能改进，但是它们或能提高性能、或能提升语法的严谨性、或能减少编码出错的机会。Java提供给
了用户大量的语法糖，比如泛型、自动装箱、自动拆箱、foreach循环、变长参数、内部类、枚举类、断言（assert）等。

##### 1.可变长度参数
```java
	public static void main(String[] args) {
		/**
		 * 输出为 1 2 3 
		 * 从输出可知： ①可变长参数必须是最后一个参数(如不是，编译器会报错)。即方法参数列表中只能有一个可变长度参数
		 * 		    ②可以使用遍历数组的方式去遍历可变参数。
		 * 			③可变参数是利用数组实现的。
		 */
		testArgs("0", "1", "2", "3");//输出为 1 2 3 
		String[] strs = {"1", "2", "3"};
		testArgs("0", strs);//输出为 1 2 3 
	}
	/**
	 * 可变长参数
	 * @param strs
	 */
	public static void testArgs(String str,String... strs) {
		for (int i = 0; i < strs.length; i++) {
			System.out.println(strs[i]);
		}
	}
```
##### 2.foreach循环
```java
public static void main(String[] args)
{
    List<String> list = new ArrayList<String>();
    list.add("111");
    list.add("222");
     
    //在编译的时候编译器会自动将对for这个关键字的使用转化为对目标的迭代器的使用
    //任何一个集合，无论是JDK提供的还是自己写的，只要想使用foreach循环遍历，就必须正确地实现Iterable接口
    for (String str : list)
    {
        System.out.println(str);
    }
}
```
##### 对于数组的foreach 其原理不同于上面的foreach，数组未实现Iterable接口
转自[Java将对于数组的foreach循环转换为对于这个数组每一个的循环引用。](http://www.importnew.com/24780.html)
```
public static void main(String[] args)
{
    int[] ints = {1,2,3,4,5};
    
    for (int i : ints)
        System.out.println(i);
}
```
##### 3.自动装箱和自动拆箱
Java为每种基本数据类型都提供了对应的包装器类型。
**Integer i = 1;**这个过程中会自动根据数值创建对应的Integer对象，这就是自动装箱。
**Integer integer = 10;int i = integer;**这个过程中会根据包装器类型自动将数据转换为基本类型，这就是自动拆箱。
```java
public void test1();
    Code:
       0: iconst_1			 /** 自动装箱:Java虚拟机会自动调用Integer的valueOf方法 **/
       1: invokestatic  #53  // Method java/lang/Integer.valueOf:(I)Ljava/lang/Integer;
       4: astore_1
       5: iconst_2
       6: invokestatic  #53  // Method java/lang/Integer.valueOf:(I)Ljava/lang/Integer;
       9: astore_2
      10: aload_2			 /** 自动拆箱:Java虚拟机会自动调用Integer的intValue方法**/
      11: invokevirtual #59  // Method java/lang/Integer.intValue:()I
      14: istore_3
      15: return
```
注意：Byte、Short、Integer、Long、Char这几个装箱类的valueOf()方法是以128位分界线做了缓存的，假如是128以下且-128以上的值是会取缓存里面的引用的，以Integer为例，其valueOf(int i)的源代码为：
```
public static Integer valueOf(int i) {
    final int offset = 128;
    if (i >= -128 && i <= 127) { // must cache 
        return IntegerCache.cache[i + offset];
    }
        return new Integer(i);
    }
```
而Float、Double则不会，原因也很简单，因为byte、Short、integer、long、char在某个范围内的整数个数是有限的，但是float、double这两个浮点数却不是。

##### 4.泛型与类型擦除

##### 5.条件编译
```
if(true){  
    System.out.println("oliver");  
}else{  
    System.out.println("lee");  
} 
``` 
       这段代码的字节码反编译后只有一条语句：
```
System.out.println("oliver");
```  
       在编译器中，将会把分支不成立的代码消除，这一动作发生在编译器解除语法糖阶段。
       所以说，可以利用条件语句来实现预编译。
##### 6.内部类
ava语言中之所以引入内部类，是因为有些时候一个类只在另一个类中有用，我们不想让其在另外一个地方被使用。
内部类之所以是语法糖，是因为其只是一个编译时的概念，一旦编译完成，编译器就会为内部类生成一个单独的class文件，
名为outer$innter.class。
##### 7.枚举类
枚举类型其实并不复杂，在JVM字节码文件结构中，并没有“枚举”这个类型。
其实源程序的枚举类型，会在编译期被编译成一个普通了类。利用继承和反射，这是完全可以做到的。
##### 8.断言语句

##### 9.泛型
